openpixels-0.3.1.dist-info/METADATA
openpixels-0.3.1.dist-info/WHEEL
openpixels-0.3.1.dist-info/entry_points.txt
openpixels-0.3.1.dist-info/licenses/LICENSE
openpixels/__init__.py
openpixels/client.py
openpixels/sample.test.py
openpixels-0.3.1.dist-info/RECORD
