Metadata-Version: 2.4
Name: openpixels
Version: 0.3.1
Summary: OpenPixels Python SDK
Author-Email: Robert <robert@openpixels.ai>
License-Expression: MIT
License-File: LICENSE
Classifier: Programming Language :: Python :: 3
Classifier: Operating System :: OS Independent
Project-URL: Homepage, https://openpixels.ai
Project-URL: Issues, https://github.com/openpixels-ai/openpixels-python/issues
Requires-Python: >=3.8
Requires-Dist: httpx>=0.28.1
Requires-Dist: httpx[http2]>=0.28.1
Provides-Extra: dev
Requires-Dist: pytest; extra == "dev"
Requires-Dist: pytest-asyncio; extra == "dev"
Requires-Dist: python-dotenv; extra == "dev"
